torrentfileQt/__init__.py
torrentfileQt/__main__.py
torrentfileQt/bencodeTab.py
torrentfileQt/checkTab.py
torrentfileQt/createTab.py
torrentfileQt/editorTab.py
torrentfileQt/infoTab.py
torrentfileQt/qss.py
torrentfileQt/rebuildTab.py
torrentfileQt/titleBar.py
torrentfileQt/toolTab.py
torrentfileQt/utils.py
torrentfileQt/version.py
torrentfileQt/window.py
torrentfileQt/assets/archive.png
torrentfileQt/assets/arrow-down.png
torrentfileQt/assets/arrow-down2.png
torrentfileQt/assets/brackets.png
torrentfileQt/assets/branch-closed.png
torrentfileQt/assets/branch-end.png
torrentfileQt/assets/branch-more.png
torrentfileQt/assets/branch-open.png
torrentfileQt/assets/browse_file.png
torrentfileQt/assets/browse_folder.png
torrentfileQt/assets/close-dark.png
torrentfileQt/assets/close-light.png
torrentfileQt/assets/data.png
torrentfileQt/assets/edit.png
torrentfileQt/assets/erase.png
torrentfileQt/assets/file.png
torrentfileQt/assets/folder.png
torrentfileQt/assets/hash.png
torrentfileQt/assets/insert.png
torrentfileQt/assets/list.png
torrentfileQt/assets/max-dark.png
torrentfileQt/assets/max-light.png
torrentfileQt/assets/min-dark.png
torrentfileQt/assets/min-light.png
torrentfileQt/assets/minus.png
torrentfileQt/assets/music.png
torrentfileQt/assets/plus.png
torrentfileQt/assets/save-as.png
torrentfileQt/assets/scale.png
torrentfileQt/assets/torrentfile.ico
torrentfileQt/assets/torrentfile48.png
torrentfileQt/assets/trash.png
torrentfileQt/assets/video.png
torrentfileQt/assets/vline.png
torrentfileQt-0.4.0.dist-info/LICENSE
torrentfileQt-0.4.0.dist-info/METADATA
torrentfileQt-0.4.0.dist-info/WHEEL
torrentfileQt-0.4.0.dist-info/entry_points.txt
torrentfileQt-0.4.0.dist-info/top_level.txt
torrentfileQt-0.4.0.dist-info/RECORD
