Metadata-Version: 2.1
Name: torrentfileQt
Version: 0.4.0
Summary: GUI based tool for creating Bittorrent files.
Author-email: alexpdev <alexpdev@pm.me>
License: Apache License
Project-URL: homepage, https://github.com/alexpdev/torrentfileQt
Project-URL: repository, https://github.com
Project-URL: issues, https://github.com/alexpdev/torrentfileQt/issues
Keywords: GUI,Bittorrent,metafile,torrentfile
Classifier: Development Status :: 4 - Beta
Classifier: Operating System :: OS Independent
Classifier: Programming Language :: Python :: 3.6
Classifier: Programming Language :: Python :: 3.7
Classifier: Programming Language :: Python :: 3.8
Classifier: Programming Language :: Python :: 3.9
Classifier: Programming Language :: Python :: 3.10
Classifier: License :: OSI Approved :: Apache Software License
Requires-Python: >=3.6
License-File: LICENSE
Requires-Dist: torrentfile
Requires-Dist: PySide6
